nottoday/__init__.py
nottoday-0.0.1.dist-info/LICENSE.txt
nottoday-0.0.1.dist-info/METADATA
nottoday-0.0.1.dist-info/WHEEL
nottoday-0.0.1.dist-info/top_level.txt
nottoday-0.0.1.dist-info/RECORD
